opik/__init__.py
opik/_logging.py
opik/config.py
opik/context_storage.py
opik/datetime_helpers.py
opik/dict_utils.py
opik/environment.py
opik/exceptions.py
opik/format_helpers.py
opik/httpx_client.py
opik/id_helpers.py
opik/jsonable_encoder.py
opik/logging_messages.py
opik/opik_context.py
opik/package_version.py
opik/py.typed
opik/s3_httpx_client.py
opik/semantic_version.py
opik/synchronization.py
opik/tracing_runtime_config.py
opik/types.py
opik/url_helpers.py
opik/anonymizer/__init__.py
opik/anonymizer/anonymizer.py
opik/anonymizer/factory.py
opik/anonymizer/recursive_anonymizer.py
opik/anonymizer/rules.py
opik/anonymizer/rules_anonymizer.py
opik/api_key/__init__.py
opik/api_key/base64_helper.py
opik/api_key/opik_api_key.py
opik/api_objects/__init__.py
opik/api_objects/constants.py
opik/api_objects/data_helpers.py
opik/api_objects/helpers.py
opik/api_objects/local_recording.py
opik/api_objects/observation_data.py
opik/api_objects/opik_client.py
opik/api_objects/opik_query_language.py
opik/api_objects/rest_stream_parser.py
opik/api_objects/search_helpers.py
opik/api_objects/validation_helpers.py
opik/api_objects/attachment/__init__.py
opik/api_objects/attachment/attachment.py
opik/api_objects/attachment/attachment_context.py
opik/api_objects/attachment/attachments_extractor.py
opik/api_objects/attachment/client.py
opik/api_objects/attachment/converters.py
opik/api_objects/attachment/decoder.py
opik/api_objects/attachment/decoder_base64.py
opik/api_objects/attachment/decoder_helpers.py
opik/api_objects/conversation/__init__.py
opik/api_objects/conversation/conversation_factory.py
opik/api_objects/conversation/conversation_thread.py
opik/api_objects/dataset/__init__.py
opik/api_objects/dataset/converters.py
opik/api_objects/dataset/dataset.py
opik/api_objects/dataset/dataset_item.py
opik/api_objects/dataset/rest_operations.py
opik/api_objects/experiment/__init__.py
opik/api_objects/experiment/experiment.py
opik/api_objects/experiment/experiment_item.py
opik-1.10.1.dist-info/licenses/LICENSE
opik-1.10.1.dist-info/METADATA
opik-1.10.1.dist-info/WHEEL
opik-1.10.1.dist-info/entry_points.txt
opik-1.10.1.dist-info/top_level.txt
opik-1.10.1.dist-info/RECORD
