Metadata-Version: 2.4
Name: opik
Version: 1.10.1
Summary: Comet tool for logging and evaluating LLM traces
Home-page: https://www.comet.com
Author: Comet ML Inc.
Author-email: mail@comet.com
License: Apache 2.0 License
Project-URL: Source code, https://github.com/comet-ml/opik
Keywords: opik
Classifier: Development Status :: 2 - Pre-Alpha
Classifier: Intended Audience :: Developers
Classifier: License :: OSI Approved :: Apache Software License
Classifier: Natural Language :: English
Classifier: Programming Language :: Python :: 3 :: Only
Classifier: Programming Language :: Python :: 3
Classifier: Programming Language :: Python :: 3.10
Classifier: Programming Language :: Python :: 3.11
Classifier: Programming Language :: Python :: 3.12
Classifier: Programming Language :: Python :: 3.13
Classifier: Programming Language :: Python :: 3.14
Requires-Python: >=3.10
License-File: LICENSE
Requires-Dist: boto3-stubs[bedrock-runtime]>=1.34.110
Requires-Dist: click
Requires-Dist: httpx
Requires-Dist: rapidfuzz<4.0.0,>=3.0.0
Requires-Dist: litellm!=1.75.0,!=1.75.1,!=1.75.2,!=1.75.3,!=1.75.4,!=1.75.5,!=1.77.3,!=1.77.4,!=1.77.5,!=1.77.7,!=1.78.0,!=1.78.2,!=1.78.3,!=1.78.4,!=1.78.5,!=1.78.6,!=1.78.7,!=1.79.0,!=1.79.1,>=1.79.2
Requires-Dist: openai
Requires-Dist: pydantic-settings!=2.9.0,<3.0.0,>=2.0.0
Requires-Dist: pydantic<3.0.0,>=2.0.0
Requires-Dist: pytest
Requires-Dist: rich
Requires-Dist: sentry_sdk>=2.0.0
Requires-Dist: tenacity
Requires-Dist: tqdm
Requires-Dist: uuid6
Requires-Dist: jinja2
Provides-Extra: proxy
Requires-Dist: fastapi>=0.100.0; extra == "proxy"
Requires-Dist: uvicorn>=0.23.0; extra == "proxy"
Dynamic: author
Dynamic: author-email
Dynamic: classifier
Dynamic: description
Dynamic: description-content-type
Dynamic: home-page
Dynamic: keywords
Dynamic: license
Dynamic: license-file
Dynamic: project-url
Dynamic: provides-extra
Dynamic: requires-dist
Dynamic: requires-python
Dynamic: summary
